{    "type" : "object",    "properties" : {        "custodian" : {            "type" : "object",            "properties" : {                "name": { "type": "string" },                "description": { "type": "string" },                "homepage": { "type": "string" },                "contact": {                    "type" : ["object", "array"],                    "properties" : {                        "name": { "type": "string" },                        "email": { "type": "string" },                        "homepage": { "type": "string" },                        "type": { "type": "string" }                    }                },                "type": { "type": "string" }            }        },        "coverage" : {            "type" : "object",            "properties" : {                "description": { "type": "string" },                "topics": { "type": ["object", "string"] },                "geography": { "type": ["object", "string"] },                "time": { "type": ["object", "string"] }            }        },        "provenance" : {            "type" : "object",            "properties" : {                "description": { "type": "string" }            }        },        "profile" : {            "type" : "object",            "properties" : {                "description": { "type": "string" }            }        },        "resources" : { "type" : ["object", "array"] }    }}